{
	"languages": {"English": "en", "Italiano": "it"},
	"it": "Italiano",
	"start": {"en": "Start", "it": "Avvia"},
    "quit": {"en": "Quit", "it": "Esci"},
    "info": {"en": "Application developed by\nMichele Righi & Karina Chichifoi\nusing ...", "it": "Applicazione sviluppata da\nMichele Righi e Karina Chichifoi\nutilizzando ..."},
    "search": {"en": "Search", "it": "Cerca"},
    "screenshot": {"en": "Screenshot", "it": "Schermata"},
    "cry": {"en": "Cry: ", "it": "Verso: "},
    "name": {"en": "Name: ", "it": "Nome: "},
    "types": {"en": "Type(s): ", "it": "Tipo/i: "},
    "hp": {"en": "HP:", "it": "PS:"},
    "attack": {"en": "Attack:", "it": "Attacco:"},
    "defense": {"en": "Defense:", "it": "Difesa:"},
    "sp. atk": {"en": "Sp. Atk:", "it": "Att. Sp.:"},
    "sp. def": {"en": "Sp. Def:", "it": "Dif. Sp.:"},
    "speed": {"en": "Speed:", "it": "Veloc.:"},
    "settings": {"en": "Settings", "it": "Impostazioni"},
    "language": {"en": "Language: ", "it": "Lingua: "},
    "full screen": {"en": "Full screen: ", "it": "Schermo int.: "},
    "descr voice": {"en": "Descr. voice: ", "it": "Voce descr.: "},
    "flip image": {"en": "Flip image: ", "it": "Specchia imm.: "},
    "volume": {"en": "Volume: ", "it": "Volume: "},
    "save": {"en": "Save", "it": "Salva"},
    "cancel": {"en": "Cancel", "it": "Annulla"},
	"time": {"en": "Time: ", "it": "Ora: "}
}